main.py
setup.py
midi_melody_extractions.egg-info/PKG-INFO
midi_melody_extractions.egg-info/SOURCES.txt
midi_melody_extractions.egg-info/dependency_links.txt
midi_melody_extractions.egg-info/requires.txt
midi_melody_extractions.egg-info/top_level.txt